LICENSE
README.md
setup.py
flask_kiteconnect/__init__.py
flask_kiteconnect.egg-info/PKG-INFO
flask_kiteconnect.egg-info/SOURCES.txt
flask_kiteconnect.egg-info/dependency_links.txt
flask_kiteconnect.egg-info/requires.txt
flask_kiteconnect.egg-info/top_level.txt